compas_occ/__init__.py
compas_occ/occ.py
compas_occ/brep/__init__.py
compas_occ/brep/brep.py
compas_occ/brep/brepedge.py
compas_occ/brep/brepface.py
compas_occ/brep/breploop.py
compas_occ/brep/brepvertex.py
compas_occ/brep/errors.py
compas_occ/conversions/__init__.py
compas_occ/conversions/arrays.py
compas_occ/conversions/geometry.py
compas_occ/conversions/meshes.py
compas_occ/conversions/transformations.py
compas_occ/geometry/__init__.py
compas_occ/geometry/curves/__init__.py
compas_occ/geometry/curves/bezier.py
compas_occ/geometry/curves/curve.py
compas_occ/geometry/curves/curve2d.py
compas_occ/geometry/curves/nurbs.py
compas_occ/geometry/surfaces/__init__.py
compas_occ/geometry/surfaces/nurbs.py
compas_occ/geometry/surfaces/surface.py
compas_occ/geometry/surfaces/__temp/extrusion.py
compas_occ/geometry/surfaces/__temp/revolution.py
compas_occ-1.2.1.dist-info/LICENSE
compas_occ-1.2.1.dist-info/METADATA
compas_occ-1.2.1.dist-info/WHEEL
compas_occ-1.2.1.dist-info/top_level.txt
compas_occ-1.2.1.dist-info/RECORD
