Metadata-Version: 2.1
Name: compas_occ
Version: 1.2.1
Summary: COMPAS wrapper for the Python bindings of OCC.
Author-email: tom van mele <tom.v.mele@gmail.com>, Lotte Aldinger <aldinger@arch.ethz.ch>, Chen Kasirer <kasirer@arch.ethz.ch>
License: MIT License
Project-URL: Homepage, https://compas-dev.github.io/compas_occ
Project-URL: Repository, https://github.com/compas-dev/compas_occ
Keywords: compas,nurbs,brep,occ
Classifier: Development Status :: 4 - Beta
Classifier: Topic :: Scientific/Engineering
Classifier: Programming Language :: Python
Classifier: Programming Language :: Python :: 3
Classifier: Programming Language :: Python :: 3.9
Classifier: Programming Language :: Python :: 3.10
Classifier: Programming Language :: Python :: 3.11
Requires-Python: >=3.9
License-File: LICENSE
Requires-Dist: compas >=2.3
Provides-Extra: dev
Requires-Dist: attrs >=17.4 ; extra == 'dev'
Requires-Dist: black >=22.12.0 ; extra == 'dev'
Requires-Dist: bump-my-version ; extra == 'dev'
Requires-Dist: compas-invocations2 ; extra == 'dev'
Requires-Dist: compas-viewer ; extra == 'dev'
Requires-Dist: invoke >=0.14 ; extra == 'dev'
Requires-Dist: ruff ; extra == 'dev'
Requires-Dist: sphinx-compas2-theme ; extra == 'dev'
Requires-Dist: twine ; extra == 'dev'
Requires-Dist: wheel ; extra == 'dev'
